cgp/__init__.py
cgp/cgp.py
cgp/config.py
cgp/utils.py
python_cgp-0.0.1.dist-info/LICENSE
python_cgp-0.0.1.dist-info/METADATA
python_cgp-0.0.1.dist-info/WHEEL
python_cgp-0.0.1.dist-info/top_level.txt
python_cgp-0.0.1.dist-info/RECORD
