Metadata-Version: 2.1
Name: python-cgp
Version: 0.0.1
Summary: A Python implementation of the correlation based glimpse proportion (CGP) index
Author-email: Philippe Gonzalez <hello@philgzl.com>
Project-URL: Homepage, https://github.com/philgzl/cgp
Project-URL: Issues, https://github.com/philgzl/cgp/issues
Classifier: Programming Language :: Python :: 3
Classifier: License :: OSI Approved :: MIT License
Classifier: Operating System :: OS Independent
Requires-Python: >=3.8
License-File: LICENSE
Requires-Dist: numpy
Requires-Dist: scipy
